{"created_at": "Fri Oct 09 19:04:29 +0000 2015", "favorited": false, "id": 652560280031883264, "lang": "en", "retweet_count": 1, "retweeted": false, "source": "<a href=\"http://www.facebook.com/twitter\" rel=\"nofollow\">Facebook</a>", "text": "Lincoln Report (UCLA Students protest after partygoers wear blackface at fraternity party)... http://t.co/wWgyiYNzzv", "truncated": false, "urls": {"http://t.co/wWgyiYNzzv": "http://fb.me/4tKAlwoYk"}, "user": {"created_at": "Wed Jul 09 01:45:47 +0000 2008", "description": "Pro Liberty Conservative Christian Homeschooler aiding others with technology to win over our fellow countrymen.", "favourites_count": 52, "followers_count": 10005, "friends_count": 10585, "geo_enabled": true, "id": 15360796, "lang": "en", "listed_count": 297, "location": "Round Lake Beach, IL", "name": "Lennie Jarratt", "profile_background_color": "2C2C99", "profile_background_image_url": "http://pbs.twimg.com/profile_background_images/47288594/OODA_twitter6.gif", "profile_background_tile": false, "profile_image_url": "https://pbs.twimg.com/profile_images/1107269577/LakeCountyTeaPartyThumbNail_normal.jpg", "profile_link_color": "6692C4", "profile_sidebar_fill_color": "9A0300", "profile_text_color": "000000", "protected": false, "screen_name": "ljarratt", "statuses_count": 523634, "time_zone": "Central Time (US & Canada)", "url": "http://t.co/zzxRLgDqtv", "utc_offset": -21600}}
{"created_at": "Sun Nov 22 20:22:47 +0000 2015", "favorite_count": 3, "favorited": false, "id": 668525050220400641, "lang": "en", "place": {"attributes": {}, "bounding_box": {"coordinates": [[[-74.332704, 40.18095], [-74.2434504, 40.18095], [-74.2434504, 40.252228], [-74.332704, 40.252228]]], "type": "Polygon"}, "contained_within": [], "country": "United States", "country_code": "US", "full_name": "West Freehold, NJ", "id": "01bb5d775f6ebee3", "name": "West Freehold", "place_type": "city", "url": "https://api.twitter.com/1.1/geo/id/01bb5d775f6ebee3.json"}, "retweeted": false, "source": "<a href=\"http://twitter.com/download/iphone\" rel=\"nofollow\">Twitter for iPhone</a>", "text": "People from Missouri state university are having a protest claiming that Abraham Lincoln was racist. I have now heard it all", "truncated": false, "user": {"created_at": "Mon Mar 25 00:49:37 +0000 2013", "default_profile": true, "description": "Freehold |Est. 1996|SJV alum", "favourites_count": 3662, "followers_count": 332, "friends_count": 285, "geo_enabled": true, "id": 1297169912, "lang": "en", "listed_count": 2, "location": "Monmouth University 19", "name": "Ryan", "profile_background_color": "C0DEED", "profile_background_image_url": "http://abs.twimg.com/images/themes/theme1/bg.png", "profile_background_tile": false, "profile_banner_url": "https://pbs.twimg.com/profile_banners/1297169912/1449699724", "profile_image_url": "https://pbs.twimg.com/profile_images/655252612049207296/f_GclFJL_normal.jpg", "profile_link_color": "0084B4", "profile_sidebar_fill_color": "DDEEF6", "profile_text_color": "333333", "protected": false, "screen_name": "Ryan_Walsh26", "statuses_count": 6045}}
{"created_at": "Mon Nov 23 18:28:34 +0000 2015", "favorited": false, "id": 668858694503804928, "lang": "en", "media": [{"display_url": "pic.twitter.com/RRQBgJ2iJM", "expanded_url": "http://twitter.com/vinnysgreen/status/668858694503804928/photo/1", "id": 668858694247907329, "id_str": "668858694247907329", "indices": [35, 58], "media_url": "http://pbs.twimg.com/media/CUhDcEuUAAErkkx.png", "media_url_https": "https://pbs.twimg.com/media/CUhDcEuUAAErkkx.png", "sizes": {"large": {"h": 341, "resize": "fit", "w": 608}, "medium": {"h": 336, "resize": "fit", "w": 600}, "small": {"h": 190, "resize": "fit", "w": 340}, "thumb": {"h": 150, "resize": "crop", "w": 150}}, "type": "photo", "url": "https://t.co/RRQBgJ2iJM"}], "retweeted": false, "source": "<a href=\"http://dlvr.it\" rel=\"nofollow\">dlvr.it</a>", "text": "Racist Abe https://t.co/cxi4fGK3ue https://t.co/RRQBgJ2iJM", "truncated": false, "urls": {"https://t.co/cxi4fGK3ue": "http://www.snopes.com/abe-lincoln-racist-protest-sign/"}, "user": {"created_at": "Tue Nov 11 20:09:34 +0000 2014", "description": "| https://t.co/Xt6XDiqOGc | https://t.co/SEI0Yy3IRo | https://t.co/Q7uZwoes2v | Marine Veteran, Ally, Political Junkie. Retweets are just retweets...", "favourites_count": 446, "followers_count": 415, "friends_count": 1740, "id": 2896866728, "lang": "en", "listed_count": 9, "location": "San Diego, CA", "name": "Vinny Green", "profile_background_color": "000000", "profile_background_image_url": "http://abs.twimg.com/images/themes/theme1/bg.png", "profile_background_tile": false, "profile_image_url": "https://pbs.twimg.com/profile_images/646510682989400064/53u-SeYI_normal.jpg", "profile_link_color": "3B94D9", "profile_sidebar_fill_color": "000000", "profile_text_color": "000000", "protected": false, "screen_name": "vinnysgreen", "statuses_count": 1713, "time_zone": "Pacific Time (US & Canada)", "url": "http://t.co/2ZoIAPUdGu", "utc_offset": -28800}}
{"created_at": "Mon Nov 23 18:35:13 +0000 2015", "favorite_count": 15, "favorited": false, "id": 668860368551337985, "lang": "en", "media": [{"display_url": "pic.twitter.com/Ioxhs4GjQM", "expanded_url": "http://twitter.com/snopes/status/668860368551337985/photo/1", "id": 668860302423932928, "id_str": "668860302423932928", "indices": [73, 96], "media_url": "http://pbs.twimg.com/media/CUhE5rpWwAAuiY0.png", "media_url_https": "https://pbs.twimg.com/media/CUhE5rpWwAAuiY0.png", "sizes": {"large": {"h": 380, "resize": "fit", "w": 423}, "medium": {"h": 380, "resize": "fit", "w": 423}, "small": {"h": 305, "resize": "fit", "w": 340}, "thumb": {"h": 150, "resize": "crop", "w": 150}}, "type": "photo", "url": "https://t.co/Ioxhs4GjQM"}], "retweet_count": 27, "retweeted": false, "source": "<a href=\"https://about.twitter.com/products/tweetdeck\" rel=\"nofollow\">TweetDeck</a>", "text": "The \"Lincoln Was Racist\" protest sign is fake. \n\nhttps://t.co/XJsGmSWc1g https://t.co/Ioxhs4GjQM", "truncated": false, "urls": {"https://t.co/XJsGmSWc1g": "http://www.snopes.com/abe-lincoln-racist-protest-sign/"}, "user": {"created_at": "Thu Apr 03 17:00:11 +0000 2008", "description": "The definitive Internet reference source for urban legends, folklore, myths, rumors, and misinformation.", "favourites_count": 12, "followers_count": 118742, "id": 14294848, "lang": "en", "listed_count": 3241, "name": "snopes.com", "profile_background_color": "C7F2B1", "profile_background_image_url": "http://pbs.twimg.com/profile_background_images/840081271/d90db0daf7c81f75aea62d88c084e755.png", "profile_background_tile": false, "profile_banner_url": "https://pbs.twimg.com/profile_banners/14294848/1365714336", "profile_image_url": "https://pbs.twimg.com/profile_images/3507964197/be9d1840411bca2d8101382340f58957_normal.png", "profile_link_color": "81D159", "profile_sidebar_fill_color": "DDEEF6", "profile_text_color": "333333", "protected": false, "screen_name": "snopes", "statuses_count": 4871, "time_zone": "Pacific Time (US & Canada)", "url": "http://t.co/10Or8rl3ff", "utc_offset": -28800, "verified": true}}
{"created_at": "Mon Nov 23 19:06:55 +0000 2015", "favorited": false, "id": 668868347845472256, "lang": "en", "retweeted": false, "source": "<a href=\"http://twitterfeed.com\" rel=\"nofollow\">twitterfeed</a>", "text": "Snopes: Racist Abe: Missouri State University students protested to get Abraham Lincoln removed from all U.S. ... https://t.co/UYwxN26b9w", "truncated": false, "urls": {"https://t.co/UYwxN26b9w": "http://bit.ly/1X9JYUn"}, "user": {"created_at": "Thu Oct 09 17:37:27 +0000 2008", "description": "Let's make critical thinking easy (and fun).", "favourites_count": 4, "followers_count": 3839, "friends_count": 677, "id": 16669742, "lang": "en", "listed_count": 272, "location": "Everywhere", "name": "Skeptic Network", "profile_background_color": "000000", "profile_background_image_url": "http://pbs.twimg.com/profile_background_images/4759267/fractile_dk.jpg", "profile_background_tile": true, "profile_banner_url": "https://pbs.twimg.com/profile_banners/16669742/1360552274", "profile_image_url": "https://pbs.twimg.com/profile_images/90185083/fractile_sing_SN3_normal.jpg", "profile_link_color": "B00B07", "profile_sidebar_fill_color": "EBECEF", "profile_text_color": "15377E", "protected": false, "screen_name": "SkepNet", "statuses_count": 18331, "time_zone": "Eastern Time (US & Canada)", "utc_offset": -18000}}
{"created_at": "Mon Nov 23 19:06:59 +0000 2015", "favorited": false, "id": 668868364358385665, "lang": "en", "retweeted": false, "source": "<a href=\"http://twitterfeed.com\" rel=\"nofollow\">twitterfeed</a>", "text": "urban legend: Missouri State University students protested to get Abraham Lincoln removed from all U.S. curren... https://t.co/cmgzBFBg8x", "truncated": false, "urls": {"https://t.co/cmgzBFBg8x": "http://bit.ly/1IbtOxw"}, "user": {"created_at": "Fri Feb 06 02:21:17 +0000 2009", "default_profile": true, "followers_count": 316, "friends_count": 33, "id": 20211460, "lang": "en", "listed_count": 12, "name": "Urban Legends", "profile_background_color": "C0DEED", "profile_background_image_url": "http://abs.twimg.com/images/themes/theme1/bg.png", "profile_background_tile": false, "profile_image_url": "https://pbs.twimg.com/profile_images/607710950532083713/MvenxG0Z_normal.jpg", "profile_link_color": "0084B4", "profile_sidebar_fill_color": "DDEEF6", "profile_text_color": "333333", "protected": false, "screen_name": "UrbanLegends", "statuses_count": 2217, "time_zone": "Eastern Time (US & Canada)", "utc_offset": -18000}}
{"created_at": "Mon Nov 23 19:07:01 +0000 2015", "favorited": false, "id": 668868370440126464, "lang": "en", "retweeted": false, "source": "<a href=\"http://twitterfeed.com\" rel=\"nofollow\">twitterfeed</a>", "text": "Snopes- Racist Abe https://t.co/CANByW5Ubx", "truncated": false, "urls": {"https://t.co/CANByW5Ubx": "http://bit.ly/1IbtOxw"}, "user": {"created_at": "Wed Oct 29 14:35:02 +0000 2008", "default_profile": true, "description": "Random Headlines", "followers_count": 122, "friends_count": 13, "id": 17042353, "lang": "en", "listed_count": 3, "location": "Random", "name": "Headline Post", "profile_background_color": "C0DEED", "profile_background_image_url": "http://abs.twimg.com/images/themes/theme1/bg.png", "profile_background_tile": false, "profile_image_url": "https://pbs.twimg.com/profile_images/63101611/headline_normal.jpg", "profile_link_color": "0084B4", "profile_sidebar_fill_color": "DDEEF6", "profile_text_color": "333333", "protected": false, "screen_name": "headlinepost", "statuses_count": 15927, "time_zone": "Central Time (US & Canada)", "utc_offset": -21600}}
{"created_at": "Mon Nov 23 19:16:34 +0000 2015", "favorite_count": 1, "favorited": false, "id": 668870777307983872, "lang": "en", "retweeted": false, "source": "<a href=\"http://twitter.com/download/android\" rel=\"nofollow\">Twitter for Android</a>", "text": "I don't know. Most of my protest signs have smudge tool marks on the edges.\nAlso, Lincoln was racist. https://t.co/3hCIbgORJK", "truncated": false, "urls": {"https://t.co/3hCIbgORJK": "https://twitter.com/snopes/status/668860368551337985"}, "user": {"created_at": "Tue May 05 23:48:23 +0000 2009", "description": "based on the short story Without You, by Del James", "favourites_count": 16205, "followers_count": 62, "friends_count": 200, "geo_enabled": true, "id": 38056294, "lang": "en", "listed_count": 5, "location": "Vancouver, WA", "name": "Thomas", "profile_background_color": "352726", "profile_background_image_url": "http://abs.twimg.com/images/themes/theme5/bg.gif", "profile_background_tile": false, "profile_banner_url": "https://pbs.twimg.com/profile_banners/38056294/1449374463", "profile_image_url": "https://pbs.twimg.com/profile_images/199367049/tom_penny_normal.jpg", "profile_link_color": "602CCF", "profile_sidebar_fill_color": "99CC33", "profile_text_color": "3E4415", "protected": false, "screen_name": "XwingGacy", "statuses_count": 5102, "time_zone": "America/Los_Angeles", "utc_offset": -28800}}
{"created_at": "Mon Nov 23 20:09:18 +0000 2015", "favorited": false, "hashtags": ["snopes"], "id": 668884047326674944, "lang": "en", "retweeted": false, "source": "<a href=\"http://twitterfeed.com\" rel=\"nofollow\">twitterfeed</a>", "text": "Racist Abe https://t.co/DypYFP5ARG via @snopes #snopes", "truncated": false, "urls": {"https://t.co/DypYFP5ARG": "http://ap236.ca/1R1CHB4"}, "user": {"created_at": "Sun May 11 21:40:42 +0000 2008", "description": "President & CEO of Journey to Diversity Workplaces. Former Barrie Green Party President. Sci-fi fan.\r\nhttp://t.co/XIvT2nHlex", "favourites_count": 193, "followers_count": 847, "friends_count": 497, "id": 14737210, "lang": "en", "listed_count": 65, "location": "Barrie, Ontario, Canada", "name": "Peter V. Tretter", "profile_background_color": "000000", "profile_background_image_url": "http://pbs.twimg.com/profile_background_images/760525136/0c706c2e6268f6ffc8a8861f3bb3511d.jpeg", "profile_background_tile": true, "profile_banner_url": "https://pbs.twimg.com/profile_banners/14737210/1419116675", "profile_image_url": "https://pbs.twimg.com/profile_images/684597586318225408/jM95qqmC_normal.jpg", "profile_link_color": "95ACF9", "profile_sidebar_fill_color": "333333", "profile_text_color": "999999", "protected": false, "screen_name": "ap236", "statuses_count": 19425, "time_zone": "Eastern Time (US & Canada)", "url": "http://t.co/YcXyy379hb", "utc_offset": -18000}, "user_mentions": [{"id": 14294848, "name": "snopes.com", "screen_name": "snopes"}]}
{"created_at": "Mon Nov 23 21:16:32 +0000 2015", "favorite_count": 1, "favorited": false, "hashtags": ["Snopes"], "id": 668900967723741184, "lang": "en", "retweet_count": 1, "retweeted": false, "source": "<a href=\"http://momknowsshopping.com/UFOParanormal\" rel=\"nofollow\">UFOParanormalNews</a>", "text": "#Snopes  Missouri State University students protested to get Abraham Lincoln removed https://t.co/AyiM9CgfDM", "truncated": false, "urls": {"https://t.co/AyiM9CgfDM": "http://goo.gl/q9nd8i"}, "user": {"created_at": "Wed Oct 01 13:34:46 +0000 2014", "description": "We provide the latest news on #UFO's, #Paranormal, #Ghosts and everything that is strange or weird. Plus #Software, #Camera's and #Computer items.", "favourites_count": 3, "followers_count": 12390, "friends_count": 11583, "geo_enabled": true, "id": 2797963749, "lang": "en", "listed_count": 414, "name": "UFO Paranormal", "profile_background_color": "000000", "profile_background_image_url": "http://abs.twimg.com/images/themes/theme1/bg.png", "profile_background_tile": false, "profile_banner_url": "https://pbs.twimg.com/profile_banners/2797963749/1419626990", "profile_image_url": "https://pbs.twimg.com/profile_images/517311356198858753/OkOTy-q6_normal.jpeg", "profile_link_color": "FA743E", "profile_sidebar_fill_color": "000000", "profile_text_color": "000000", "protected": false, "screen_name": "UFOParanormNews", "statuses_count": 77258, "url": "https://t.co/I4rmVNErYQ"}}
{"created_at": "Mon Nov 23 21:17:02 +0000 2015", "favorited": false, "hashtags": ["Racist", "factcheck", "snopes"], "id": 668901090369384448, "lang": "en", "retweeted": false, "source": "<a href=\"http://twitter.com/download/iphone\" rel=\"nofollow\">Twitter for iPhone</a>", "text": "Was Pres. Lincoln #Racist? NO\n#factcheck \n\n#snopes.com https://t.co/NVfgYQx9N8", "truncated": false, "urls": {"https://t.co/NVfgYQx9N8": "http://www.snopes.com/abe-lincoln-racist-protest-sign/"}, "user": {"created_at": "Sun Nov 28 06:26:00 +0000 2010", "default_profile": true, "description": "Veteran, Counselor, Psychologist, Teacher,Behavior, Nature, Horses, Wildlife,History, Health, Holism, Justice, Peace; \u13deOVE & BE \u041aIND / RT Does Not = Agreement", "favourites_count": 19716, "followers_count": 1807, "friends_count": 2422, "id": 220584725, "lang": "en", "listed_count": 422, "location": "Adventuring/Exploring", "name": "Angel", "profile_background_color": "C0DEED", "profile_background_image_url": "http://abs.twimg.com/images/themes/theme1/bg.png", "profile_background_tile": false, "profile_banner_url": "https://pbs.twimg.com/profile_banners/220584725/1447568414", "profile_image_url": "https://pbs.twimg.com/profile_images/665731842755047425/dBMOY-H-_normal.jpg", "profile_link_color": "0084B4", "profile_sidebar_fill_color": "DDEEF6", "profile_text_color": "333333", "protected": false, "screen_name": "IndigoHawthorne", "statuses_count": 85674, "url": "https://t.co/hBQmQtvYCT"}}
{"created_at": "Tue Nov 24 13:09:39 +0000 2015", "favorited": false, "id": 669140826795081733, "lang": "en", "retweeted": false, "source": "<a href=\"https://mobile.twitter.com\" rel=\"nofollow\">Mobile Web (M5)</a>", "text": "Protest cats should target first, the most publicly outspoken racist and white supremacist of all American presidents \u2013 Abraham Lincoln.", "truncated": false, "user": {"created_at": "Mon Aug 04 02:08:04 +0000 2008", "description": "#Father #writer #scholar #scientist [Torrance Stephens, PhD] If you value tweets, Donate Bitcoin: 163jCMr5GQwivrZZqDDgqkMGeYtnGLNuAX", "favourites_count": 1345, "followers_count": 8105, "friends_count": 155, "id": 15717071, "lang": "en", "listed_count": 269, "location": "#partsunknown", "name": "thoughtcrime", "profile_background_color": "1A1B1F", "profile_background_image_url": "http://pbs.twimg.com/profile_background_images/25391510/torancead1.jpg", "profile_background_tile": false, "profile_banner_url": "https://pbs.twimg.com/profile_banners/15717071/1440419498", "profile_image_url": "https://pbs.twimg.com/profile_images/687020927318622208/GLx8oeRn_normal.jpg", "profile_link_color": "2FC2EF", "profile_sidebar_fill_color": "252429", "profile_text_color": "666666", "protected": false, "screen_name": "RawDawgBuffalo", "statuses_count": 321862, "time_zone": "Eastern Time (US & Canada)", "url": "http://t.co/Kvv7TcwpcT", "utc_offset": -18000}}
{"created_at": "Tue Nov 24 14:41:40 +0000 2015", "favorited": false, "id": 669163981957820416, "in_reply_to_screen_name": "PantherAR15", "in_reply_to_status_id": 668823828475355136, "in_reply_to_user_id": 408219053, "lang": "en", "retweeted": false, "source": "<a href=\"http://twitter.com\" rel=\"nofollow\">Twitter Web Client</a>", "text": "@PantherAR15 @SeanSean252 The photo is a fake, and an obvious one. Took about 15 seconds of googling to figure out.  https://t.co/dW3elE7xEa", "truncated": false, "urls": {"https://t.co/dW3elE7xEa": "http://www.snopes.com/abe-lincoln-racist-protest-sign/"}, "user": {"created_at": "Fri Oct 15 13:32:07 +0000 2010", "description": "PhD candidate in MIT's Dept. of Science, Technology, & Society (HASTS).      animals, civil liberties, national security, & freedom of information", "favourites_count": 6640, "followers_count": 3088, "friends_count": 525, "geo_enabled": true, "id": 203071854, "lang": "en", "listed_count": 131, "name": "Ryan Shapiro", "profile_background_color": "1A1B1F", "profile_background_image_url": "http://abs.twimg.com/images/themes/theme9/bg.gif", "profile_background_tile": false, "profile_banner_url": "https://pbs.twimg.com/profile_banners/203071854/1401731429", "profile_image_url": "https://pbs.twimg.com/profile_images/672843101631737856/ZVkB3PMM_normal.jpg", "profile_link_color": "050505", "profile_sidebar_fill_color": "252429", "profile_text_color": "666666", "protected": false, "screen_name": "_rshapiro", "statuses_count": 5881, "time_zone": "Quito", "url": "http://t.co/0oRsQ8ymmg", "utc_offset": -18000}, "user_mentions": [{"id": 408219053, "name": "Panther", "screen_name": "PantherAR15"}, {"id": 1863840511, "name": "Sean", "screen_name": "SeanSean252"}]}
{"created_at": "Tue Nov 24 14:50:10 +0000 2015", "favorited": false, "id": 669166120276992000, "lang": "en", "retweeted": false, "source": "<a href=\"http://twitter.com\" rel=\"nofollow\">Twitter Web Client</a>", "text": "Photoshop skills Matter!  https://t.co/24UhILipOU", "truncated": false, "urls": {"https://t.co/24UhILipOU": "http://www.snopes.com/abe-lincoln-racist-protest-sign/"}, "user": {"created_at": "Wed Nov 12 21:29:10 +0000 2008", "description": "It's getting all political up in here!  I'm either laughing from the debates or in shock from a Candidate's last statement.", "favourites_count": 498, "followers_count": 407, "friends_count": 701, "id": 17349277, "lang": "en", "listed_count": 24, "location": "Chicago", "name": "Patrick", "profile_background_color": "352726", "profile_background_image_url": "http://pbs.twimg.com/profile_background_images/442036639393525760/OOVtIkaZ.jpeg", "profile_background_tile": false, "profile_banner_url": "https://pbs.twimg.com/profile_banners/17349277/1445650885", "profile_image_url": "https://pbs.twimg.com/profile_images/684780460807946245/YGVAgMaW_normal.jpg", "profile_link_color": "89C9FA", "profile_sidebar_fill_color": "99CC33", "profile_text_color": "3E4415", "protected": false, "screen_name": "pjohnphoto", "statuses_count": 6382, "time_zone": "Central Time (US & Canada)", "utc_offset": -21600}}
{"created_at": "Tue Nov 24 18:43:18 +0000 2015", "favorited": false, "id": 669224792252268544, "lang": "en", "retweeted": false, "source": "<a href=\"http://www.apple.com\" rel=\"nofollow\">iOS</a>", "text": "Racist Abe : https://t.co/Pk0oGnCmUc &gt; just in case you believed that shit. https://t.co/arjGC0bZM8", "truncated": false, "urls": {"https://t.co/Pk0oGnCmUc": "http://snopes.com", "https://t.co/arjGC0bZM8": "http://www.snopes.com/abe-lincoln-racist-protest-sign/"}, "user": {"created_at": "Wed Jun 09 02:39:11 +0000 2010", "description": "Eat well, dance dirty, respect nature Ecuadorian-American blogger Dallas, TX I love glamorous, sustainable things \u00a1Celebra la vida! https://t.co/sFauozQWju", "favourites_count": 3380, "followers_count": 4322, "friends_count": 1294, "geo_enabled": true, "id": 153642560, "lang": "en", "listed_count": 112, "location": "www.instagram.com/allyfiesta ", "name": "Ally Fiesta", "profile_background_color": "000000", "profile_background_image_url": "http://abs.twimg.com/images/themes/theme10/bg.gif", "profile_background_tile": false, "profile_banner_url": "https://pbs.twimg.com/profile_banners/153642560/1441665062", "profile_image_url": "https://pbs.twimg.com/profile_images/676964708067516416/IrzePXY7_normal.jpg", "profile_link_color": "4A913C", "profile_sidebar_fill_color": "000000", "profile_text_color": "000000", "protected": false, "screen_name": "AllyFiesta", "statuses_count": 37660, "time_zone": "Mountain Time (US & Canada)", "url": "https://t.co/rPjH4DfTgB", "utc_offset": -25200}}
{"created_at": "Tue Nov 24 19:03:57 +0000 2015", "favorited": false, "id": 669229989422845952, "in_reply_to_screen_name": "rockinrobyn59", "in_reply_to_status_id": 669228834995109888, "in_reply_to_user_id": 151284118, "lang": "en", "retweeted": false, "source": "<a href=\"https://about.twitter.com/products/tweetdeck\" rel=\"nofollow\">TweetDeck</a>", "text": "@rockinrobyn59 dont worry Robin. it TOO is fake.\nhttps://t.co/RNwGZuzTp2\n\n@peddoc63 @deneenborelli @Pieter_Gericke", "truncated": false, "urls": {"https://t.co/RNwGZuzTp2": "http://www.snopes.com/abe-lincoln-racist-protest-sign/"}, "user": {"created_at": "Wed Oct 01 04:25:11 +0000 2008", "favourites_count": 8535, "followers_count": 822, "friends_count": 278, "id": 16540169, "lang": "en", "listed_count": 77, "location": "Eagle Rock, CA  90041", "name": "BWANA86", "profile_background_color": "1A1B1F", "profile_background_image_url": "http://pbs.twimg.com/profile_background_images/860599298/785f15db4bc9971a4db6e241d8b4e157.jpeg", "profile_background_tile": true, "profile_banner_url": "https://pbs.twimg.com/profile_banners/16540169/1398386609", "profile_image_url": "https://pbs.twimg.com/profile_images/638143564501807104/OTPFdjCE_normal.jpg", "profile_link_color": "2FC2EF", "profile_sidebar_fill_color": "252429", "profile_text_color": "666666", "protected": false, "screen_name": "Bwana86", "statuses_count": 123125, "time_zone": "Pacific Time (US & Canada)", "utc_offset": -28800}, "user_mentions": [{"id": 151284118, "name": "Robyn Harms", "screen_name": "rockinrobyn59"}, {"id": 1379288282, "name": "Feisty\u2600\ufe0fFloridian", "screen_name": "peddoc63"}, {"id": 76438819, "name": "Deneen Borelli", "screen_name": "deneenborelli"}, {"id": 897789679, "name": "JR Ewing", "screen_name": "Pieter_Gericke"}]}
{"created_at": "Tue Nov 24 19:04:14 +0000 2015", "favorited": false, "id": 669230058813456384, "in_reply_to_screen_name": "peddoc63", "in_reply_to_status_id": 668819147304865793, "in_reply_to_user_id": 1379288282, "lang": "en", "retweeted": false, "source": "<a href=\"https://about.twitter.com/products/tweetdeck\" rel=\"nofollow\">TweetDeck</a>", "text": "@peddoc63 fake photo.\nwhy are you so dumb and gullible?\nhttps://t.co/RNwGZuzTp2\n@deneenborelli @Pieter_Gericke", "truncated": false, "urls": {"https://t.co/RNwGZuzTp2": "http://www.snopes.com/abe-lincoln-racist-protest-sign/"}, "user": {"created_at": "Wed Oct 01 04:25:11 +0000 2008", "favourites_count": 8535, "followers_count": 822, "friends_count": 278, "id": 16540169, "lang": "en", "listed_count": 77, "location": "Eagle Rock, CA  90041", "name": "BWANA86", "profile_background_color": "1A1B1F", "profile_background_image_url": "http://pbs.twimg.com/profile_background_images/860599298/785f15db4bc9971a4db6e241d8b4e157.jpeg", "profile_background_tile": true, "profile_banner_url": "https://pbs.twimg.com/profile_banners/16540169/1398386609", "profile_image_url": "https://pbs.twimg.com/profile_images/638143564501807104/OTPFdjCE_normal.jpg", "profile_link_color": "2FC2EF", "profile_sidebar_fill_color": "252429", "profile_text_color": "666666", "protected": false, "screen_name": "Bwana86", "statuses_count": 123125, "time_zone": "Pacific Time (US & Canada)", "utc_offset": -28800}, "user_mentions": [{"id": 1379288282, "name": "Feisty\u2600\ufe0fFloridian", "screen_name": "peddoc63"}, {"id": 76438819, "name": "Deneen Borelli", "screen_name": "deneenborelli"}, {"id": 897789679, "name": "JR Ewing", "screen_name": "Pieter_Gericke"}]}
{"created_at": "Tue Nov 24 19:12:29 +0000 2015", "favorited": false, "id": 669232137451782144, "in_reply_to_screen_name": "rockinrobyn59", "in_reply_to_status_id": 669230936450445312, "in_reply_to_user_id": 151284118, "lang": "en", "retweeted": false, "source": "<a href=\"https://about.twitter.com/products/tweetdeck\" rel=\"nofollow\">TweetDeck</a>", "text": "@rockinrobyn59 \nanswer: NO, its not true \nhttps://t.co/RNwGZuzTp2\n\n@peddoc63 @deneenborelli @Pieter_Gericke", "truncated": false, "urls": {"https://t.co/RNwGZuzTp2": "http://www.snopes.com/abe-lincoln-racist-protest-sign/"}, "user": {"created_at": "Wed Oct 01 04:25:11 +0000 2008", "favourites_count": 8535, "followers_count": 822, "friends_count": 278, "id": 16540169, "lang": "en", "listed_count": 77, "location": "Eagle Rock, CA  90041", "name": "BWANA86", "profile_background_color": "1A1B1F", "profile_background_image_url": "http://pbs.twimg.com/profile_background_images/860599298/785f15db4bc9971a4db6e241d8b4e157.jpeg", "profile_background_tile": true, "profile_banner_url": "https://pbs.twimg.com/profile_banners/16540169/1398386609", "profile_image_url": "https://pbs.twimg.com/profile_images/638143564501807104/OTPFdjCE_normal.jpg", "profile_link_color": "2FC2EF", "profile_sidebar_fill_color": "252429", "profile_text_color": "666666", "protected": false, "screen_name": "Bwana86", "statuses_count": 123125, "time_zone": "Pacific Time (US & Canada)", "utc_offset": -28800}, "user_mentions": [{"id": 151284118, "name": "Robyn Harms", "screen_name": "rockinrobyn59"}, {"id": 1379288282, "name": "Feisty\u2600\ufe0fFloridian", "screen_name": "peddoc63"}, {"id": 76438819, "name": "Deneen Borelli", "screen_name": "deneenborelli"}, {"id": 897789679, "name": "JR Ewing", "screen_name": "Pieter_Gericke"}]}
{"created_at": "Tue Nov 24 19:35:59 +0000 2015", "favorited": false, "id": 669238049646190592, "in_reply_to_screen_name": "TeeTee1119", "in_reply_to_status_id": 669237642828058624, "in_reply_to_user_id": 744008064, "lang": "en", "retweeted": false, "source": "<a href=\"https://about.twitter.com/products/tweetdeck\" rel=\"nofollow\">TweetDeck</a>", "text": "@TeeTee1119 https://t.co/RNwGZuzTp2\n\nenjoy your crow", "truncated": false, "urls": {"https://t.co/RNwGZuzTp2": "http://www.snopes.com/abe-lincoln-racist-protest-sign/"}, "user": {"created_at": "Wed Oct 01 04:25:11 +0000 2008", "favourites_count": 8535, "followers_count": 822, "friends_count": 278, "id": 16540169, "lang": "en", "listed_count": 77, "location": "Eagle Rock, CA  90041", "name": "BWANA86", "profile_background_color": "1A1B1F", "profile_background_image_url": "http://pbs.twimg.com/profile_background_images/860599298/785f15db4bc9971a4db6e241d8b4e157.jpeg", "profile_background_tile": true, "profile_banner_url": "https://pbs.twimg.com/profile_banners/16540169/1398386609", "profile_image_url": "https://pbs.twimg.com/profile_images/638143564501807104/OTPFdjCE_normal.jpg", "profile_link_color": "2FC2EF", "profile_sidebar_fill_color": "252429", "profile_text_color": "666666", "protected": false, "screen_name": "Bwana86", "statuses_count": 123125, "time_zone": "Pacific Time (US & Canada)", "utc_offset": -28800}, "user_mentions": [{"id": 744008064, "name": "tee tee", "screen_name": "TeeTee1119"}]}
{"created_at": "Sun Dec 20 16:50:19 +0000 2015", "favorite_count": 1, "favorited": false, "id": 678618441356435456, "in_reply_to_screen_name": "drfessel", "in_reply_to_status_id": 678618280106397697, "in_reply_to_user_id": 189366606, "lang": "en", "retweeted": false, "source": "<a href=\"https://about.twitter.com/products/tweetdeck\" rel=\"nofollow\">TweetDeck</a>", "text": "@drfessel @KassandraTroy Yeah, just reading on snopes - I should have checked there first. https://t.co/0VyNfmIH8x", "truncated": false, "urls": {"https://t.co/0VyNfmIH8x": "http://www.snopes.com/abe-lincoln-racist-protest-sign/"}, "user": {"created_at": "Fri Oct 12 17:53:33 +0000 2012", "description": "Dad. Husband. Walker. Coder. Board-gamer. Northerner. MIND volunteer. CAGW Apostate. Play the ball not the man. Amateur photographer: https://t.co/FaTBAvViir", "favourites_count": 217, "followers_count": 517, "friends_count": 336, "id": 876098142, "lang": "en", "listed_count": 30, "location": "127.0.0.1", "name": "Derek Sorensen", "profile_background_color": "C0DEED", "profile_background_image_url": "http://pbs.twimg.com/profile_background_images/640317551109648384/ngPDGDwp.jpg", "profile_background_tile": false, "profile_banner_url": "https://pbs.twimg.com/profile_banners/876098142/1412714736", "profile_image_url": "https://pbs.twimg.com/profile_images/2709591083/3c4ccaf512ba84fd2558705dee4c0f6e_normal.jpeg", "profile_link_color": "0084B4", "profile_sidebar_fill_color": "000000", "profile_text_color": "000000", "protected": false, "screen_name": "th3Derek", "statuses_count": 19903, "time_zone": "Casablanca", "url": "http://t.co/2Z15ZxAiDy"}, "user_mentions": [{"id": 189366606, "name": "Penthouse Sidebar", "screen_name": "drfessel"}, {"id": 15427912, "name": "\u2605 \u0198\u03b1\u0455\u0455\u03b1\u03b7\u2202\u044f\u03b1", "screen_name": "KassandraTroy"}]}
