{"created_at": "Fri Aug 28 14:12:32 +0000 2015", "favorited": false, "hashtags": ["BachPanMein"], "id": 637266516937846790, "lang": "en", "retweeted": false, "source": "<a href=\"http://twitter.com\" rel=\"nofollow\">Twitter Web Client</a>", "text": "#BachPanMein  Cartoon network super awesome tha, Powerpuff Girls, Swat Cats,Thunder Cats,Captain Planet,Tom n Jerry,Johny Bravo n ab shit ha", "truncated": false, "user": {"created_at": "Fri Oct 16 05:44:50 +0000 2009", "description": "Remembr death a Life time Lesson.Allah loves Repentence.i tweet Kushbo Laga kr n follow non but my heart #ProudNikamma #Muslim #TeamMiswak  #Engineer #Blogger", "favourites_count": 8236, "followers_count": 891, "friends_count": 349, "geo_enabled": true, "id": 82809476, "lang": "en", "listed_count": 8, "location": "Pakistan ,Peshawar", "name": "Farhan Bin Khalid", "profile_background_color": "C0DEED", "profile_background_image_url": "http://pbs.twimg.com/profile_background_images/378800000094091904/a2ab28de140f5e0642f50c023921ed1d.jpeg", "profile_background_tile": true, "profile_banner_url": "https://pbs.twimg.com/profile_banners/82809476/1430556439", "profile_image_url": "https://pbs.twimg.com/profile_images/671375088063799296/_Bt9rvuy_normal.jpg", "profile_link_color": "4A913C", "profile_sidebar_fill_color": "DDEEF6", "profile_text_color": "333333", "protected": false, "screen_name": "WailaInsan", "statuses_count": 22578, "time_zone": "Arizona", "url": "http://t.co/nPw5W3r515", "utc_offset": -25200}}
{"created_at": "Sun Sep 06 05:12:12 +0000 2015", "favorite_count": 3, "favorited": false, "id": 640392031785775104, "in_reply_to_screen_name": "ohohyknow", "in_reply_to_status_id": 640391061861302272, "in_reply_to_user_id": 356656017, "lang": "en", "retweet_count": 5, "retweeted": false, "source": "<a href=\"http://twitter.com/download/android\" rel=\"nofollow\">Twitter for Android</a>", "text": "@ohohyknow @BlossomTPPG @BubblesTPPG @ButtercupTPPG hello there Powerpuff girls \ud83d\ude02\ud83d\ude02 I wonder if johny bravo &amp; bettyboop will come 2", "truncated": false, "user": {"created_at": "Tue Sep 01 17:31:46 +0000 2015", "default_profile": true, "favourites_count": 650, "followers_count": 54, "friends_count": 61, "id": 3416961192, "lang": "en", "listed_count": 1, "name": "Binary", "profile_background_color": "C0DEED", "profile_background_image_url": "http://abs.twimg.com/images/themes/theme1/bg.png", "profile_background_tile": false, "profile_image_url": "https://pbs.twimg.com/profile_images/646283607556788224/r3xb7TYz_normal.png", "profile_link_color": "0084B4", "profile_sidebar_fill_color": "DDEEF6", "profile_text_color": "333333", "protected": false, "screen_name": "Binary01110", "statuses_count": 2407}, "user_mentions": [{"id": 356656017, "name": "bitheway", "screen_name": "ohohyknow"}, {"id": 3231498888, "name": "B L O S S O M", "screen_name": "BlossomTPPG"}, {"id": 2384716886, "name": "B U B B L E S", "screen_name": "BubblesTPPG"}, {"id": 2476739936, "name": "B U T T E R C U P", "screen_name": "ButtercupTPPG"}]}
{"created_at": "Wed Sep 23 17:11:40 +0000 2015", "favorited": false, "id": 646733681944600576, "in_reply_to_screen_name": "Mashroomized", "in_reply_to_status_id": 646731628044263424, "in_reply_to_user_id": 64128280, "lang": "en", "retweeted": false, "source": "<a href=\"http://twitter.com/download/iphone\" rel=\"nofollow\">Twitter for iPhone</a>", "text": "@Mashroomized what about Dexters lab, Johny Bravo, Powerpuff Girls, etc?", "truncated": false, "user": {"created_at": "Thu May 10 01:50:13 +0000 2012", "description": "An incredibly flamboyant rainbow paintpup Also that nerd who runs Askteamspirit Irispin, and other tumblrs I never use Obsessed with MOTHER - AD - @azuraraconAD", "favourites_count": 6779, "followers_count": 251, "friends_count": 906, "id": 575920530, "lang": "en", "location": "Merritt Island, Florida", "name": "Spoopy Smeargle", "profile_background_color": "DD2E44", "profile_background_image_url": "http://pbs.twimg.com/profile_background_images/630365192338079744/Ged1D6kN.png", "profile_background_tile": false, "profile_banner_url": "https://pbs.twimg.com/profile_banners/575920530/1439125363", "profile_image_url": "https://pbs.twimg.com/profile_images/624142345731112960/f77-m9hG_normal.jpg", "profile_link_color": "FA743E", "profile_sidebar_fill_color": "DDEEF6", "profile_text_color": "333333", "protected": false, "screen_name": "AzuraRacon", "statuses_count": 2739, "time_zone": "Pacific Time (US & Canada)", "url": "http://t.co/vfvB7V3IUw", "utc_offset": -28800}, "user_mentions": [{"id": 64128280, "name": "Jose", "screen_name": "Mashroomized"}]}
{"created_at": "Sun Sep 27 09:58:11 +0000 2015", "favorited": false, "id": 648074146648166401, "lang": "en", "retweeted": false, "source": "<a href=\"http://twitter.com/download/android\" rel=\"nofollow\">Twitter for Android</a>", "text": "Johny Bravo,Powerpuff Girls, Kids Next Door, Courage the Cowardly Dog,The Grim Adventures of Billy n Mandy, Dexter's Labtry, n Ed,Edd n'Eddy", "truncated": false, "user": {"created_at": "Fri May 15 13:59:19 +0000 2015", "default_profile": true, "description": "Act without expectation", "favourites_count": 73, "followers_count": 54, "friends_count": 80, "geo_enabled": true, "id": 3196408849, "lang": "en", "name": "shinbeii", "profile_background_color": "C0DEED", "profile_background_image_url": "http://abs.twimg.com/images/themes/theme1/bg.png", "profile_background_tile": false, "profile_banner_url": "https://pbs.twimg.com/profile_banners/3196408849/1443191536", "profile_image_url": "https://pbs.twimg.com/profile_images/664813926639665153/hzGPfWQ3_normal.jpg", "profile_link_color": "0084B4", "profile_sidebar_fill_color": "DDEEF6", "profile_text_color": "333333", "protected": false, "screen_name": "irfan_moktar", "statuses_count": 522}}
{"created_at": "Mon Sep 28 16:44:17 +0000 2015", "favorited": false, "id": 648538733382230016, "in_reply_to_screen_name": "sketchy_desire", "in_reply_to_status_id": 648537277602201600, "in_reply_to_user_id": 3258854672, "lang": "en", "retweeted": false, "source": "<a href=\"http://twitter.com\" rel=\"nofollow\">Twitter Web Client</a>", "text": "@miss_k_tweets Like Dexter's Laboratory, Johny Bravo, Tom &amp; Jerry, Scooby Doo, The Powerpuff Girls, The Mask, Popeye, Aladdin etc \ud83d\ude0a\ud83d\ude0a", "truncated": false, "user": {"created_at": "Fri Oct 14 03:29:53 +0000 2011", "description": "Another Proud Indian! Avid Football & Cricket fan. Amateur biker! Music freak, foodie & a huge admirer of Indian Army! HUMANITY above all!", "favourites_count": 1184, "followers_count": 2277, "friends_count": 1483, "geo_enabled": true, "id": 390525205, "lang": "en", "listed_count": 29, "location": "Calcutta, India", "name": "Deep", "profile_background_color": "B2DFDA", "profile_background_image_url": "http://abs.twimg.com/images/themes/theme13/bg.gif", "profile_background_tile": false, "profile_banner_url": "https://pbs.twimg.com/profile_banners/390525205/1442935497", "profile_image_url": "https://pbs.twimg.com/profile_images/680772405841670144/CKAc1ROj_normal.jpg", "profile_link_color": "93A644", "profile_sidebar_fill_color": "FFFFFF", "profile_text_color": "333333", "protected": false, "screen_name": "CricManiacDeep", "statuses_count": 79520, "time_zone": "New Delhi", "utc_offset": 19800}}
{"created_at": "Fri Oct 23 18:27:25 +0000 2015", "favorite_count": 9, "favorited": false, "id": 657624381208854528, "lang": "en", "media": [{"display_url": "pic.twitter.com/QvnkjQJ2ZT", "expanded_url": "http://twitter.com/snopes/status/657624381208854528/photo/1", "id": 657624380558589952, "id_str": "657624380558589952", "indices": [89, 112], "media_url": "http://pbs.twimg.com/media/CSBZ487UwAAbOro.jpg", "media_url_https": "https://pbs.twimg.com/media/CSBZ487UwAAbOro.jpg", "sizes": {"large": {"h": 481, "resize": "fit", "w": 745}, "medium": {"h": 387, "resize": "fit", "w": 600}, "small": {"h": 219, "resize": "fit", "w": 340}, "thumb": {"h": 150, "resize": "crop", "w": 150}}, "type": "photo", "url": "https://t.co/QvnkjQJ2ZT"}], "retweet_count": 9, "retweeted": false, "source": "<a href=\"http://twitter.com\" rel=\"nofollow\">Twitter Web Client</a>", "text": "Posters for Johnny Bravo and Powerpuff Girls movies aren't real: https://t.co/0YhLC4MnRU https://t.co/QvnkjQJ2ZT", "truncated": false, "urls": {"https://t.co/0YhLC4MnRU": "http://bit.ly/1i15cQS"}, "user": {"created_at": "Thu Apr 03 17:00:11 +0000 2008", "description": "The definitive Internet reference source for urban legends, folklore, myths, rumors, and misinformation.", "favourites_count": 12, "followers_count": 118578, "id": 14294848, "lang": "en", "listed_count": 3236, "name": "snopes.com", "profile_background_color": "C7F2B1", "profile_background_image_url": "http://pbs.twimg.com/profile_background_images/840081271/d90db0daf7c81f75aea62d88c084e755.png", "profile_background_tile": false, "profile_banner_url": "https://pbs.twimg.com/profile_banners/14294848/1365714336", "profile_image_url": "https://pbs.twimg.com/profile_images/3507964197/be9d1840411bca2d8101382340f58957_normal.png", "profile_link_color": "81D159", "profile_sidebar_fill_color": "DDEEF6", "profile_text_color": "333333", "protected": false, "screen_name": "snopes", "statuses_count": 4852, "time_zone": "Pacific Time (US & Canada)", "url": "http://t.co/10Or8rl3ff", "utc_offset": -28800, "verified": true}}
{"created_at": "Fri Oct 23 18:29:08 +0000 2015", "favorited": false, "id": 657624815004549120, "lang": "en", "media": [{"display_url": "pic.twitter.com/e7G3I7TXqK", "expanded_url": "http://twitter.com/vinnysgreen/status/657624815004549120/photo/1", "id": 657624814757150720, "id_str": "657624814757150720", "indices": [37, 60], "media_url": "http://pbs.twimg.com/media/CSBaSOcVAAAE7k4.jpg", "media_url_https": "https://pbs.twimg.com/media/CSBaSOcVAAAE7k4.jpg", "sizes": {"large": {"h": 481, "resize": "fit", "w": 745}, "medium": {"h": 387, "resize": "fit", "w": 600}, "small": {"h": 219, "resize": "fit", "w": 340}, "thumb": {"h": 150, "resize": "crop", "w": 150}}, "type": "photo", "url": "https://t.co/e7G3I7TXqK"}], "retweeted": false, "source": "<a href=\"http://dlvr.it\" rel=\"nofollow\">dlvr.it</a>", "text": "Movie Posers https://t.co/BFfnHbfAf5 https://t.co/e7G3I7TXqK", "truncated": false, "urls": {"https://t.co/BFfnHbfAf5": "http://www.snopes.com/johny-bravo-the-rock-powerpuff-girls/"}, "user": {"created_at": "Tue Nov 11 20:09:34 +0000 2014", "description": "| https://t.co/Xt6XDiqOGc | https://t.co/SEI0Yy3IRo | https://t.co/Q7uZwoes2v | Marine Veteran, Ally, Political Junkie. Retweets are just retweets...", "favourites_count": 446, "followers_count": 416, "friends_count": 1736, "id": 2896866728, "lang": "en", "listed_count": 9, "location": "San Diego, CA", "name": "Vinny Green", "profile_background_color": "000000", "profile_background_image_url": "http://abs.twimg.com/images/themes/theme1/bg.png", "profile_background_tile": false, "profile_image_url": "https://pbs.twimg.com/profile_images/646510682989400064/53u-SeYI_normal.jpg", "profile_link_color": "3B94D9", "profile_sidebar_fill_color": "000000", "profile_text_color": "000000", "protected": false, "screen_name": "vinnysgreen", "statuses_count": 1695, "time_zone": "Pacific Time (US & Canada)", "url": "http://t.co/2ZoIAPUdGu", "utc_offset": -28800}}
{"created_at": "Fri Oct 23 18:30:19 +0000 2015", "favorited": false, "id": 657625110493425664, "lang": "en", "media": [{"display_url": "pic.twitter.com/TlNqbFFHTz", "expanded_url": "http://twitter.com/snopes/status/657624381208854528/photo/1", "id": 657624380558589952, "id_str": "657624380558589952", "indices": [89, 112], "media_url": "http://pbs.twimg.com/media/CSBZ487UwAAbOro.jpg", "media_url_https": "https://pbs.twimg.com/media/CSBZ487UwAAbOro.jpg", "sizes": {"large": {"h": 481, "resize": "fit", "w": 745}, "medium": {"h": 387, "resize": "fit", "w": 600}, "small": {"h": 219, "resize": "fit", "w": 340}, "thumb": {"h": 150, "resize": "crop", "w": 150}}, "source_status_id": 657624381208854528, "source_status_id_str": "657624381208854528", "source_user_id": 14294848, "source_user_id_str": "14294848", "type": "photo", "url": "https://t.co/TlNqbFFHTz"}], "retweeted": false, "source": "<a href=\"http://ifttt.com\" rel=\"nofollow\">IFTTT</a>", "text": "Posters for Johnny Bravo and Powerpuff Girls movies aren't real: https://t.co/nAfF23C7HQ https://t.co/TlNqbFFHTz", "truncated": false, "urls": {"https://t.co/nAfF23C7HQ": "http://bit.ly/1i15cQS"}, "user": {"created_at": "Mon Jan 28 14:40:52 +0000 2013", "default_profile": true, "description": "I tweet about all things in Cape Town. #CapeFact The Mother City. For info in events: #CapeEvents. Also #capetownfairy me for any quests", "favourites_count": 661, "followers_count": 2623, "friends_count": 2736, "id": 1128255048, "lang": "en", "listed_count": 90, "location": "Cape Town", "name": "Cape Town Fairy", "profile_background_color": "C0DEED", "profile_background_image_url": "http://abs.twimg.com/images/themes/theme1/bg.png", "profile_background_tile": false, "profile_banner_url": "https://pbs.twimg.com/profile_banners/1128255048/1359385361", "profile_image_url": "https://pbs.twimg.com/profile_images/3175089990/ddcec258fe970be63266d343dc094577_normal.png", "profile_link_color": "0084B4", "profile_sidebar_fill_color": "DDEEF6", "profile_text_color": "333333", "protected": false, "screen_name": "CapeTownFairy", "statuses_count": 73095, "time_zone": "Athens", "utc_offset": 7200}}
{"created_at": "Fri Oct 23 18:32:07 +0000 2015", "favorited": false, "id": 657625564140826624, "lang": "en", "media": [{"display_url": "pic.twitter.com/zbfjVnyu62", "expanded_url": "http://twitter.com/snopes/status/657624381208854528/photo/1", "id": 657624380558589952, "id_str": "657624380558589952", "indices": [89, 112], "media_url": "http://pbs.twimg.com/media/CSBZ487UwAAbOro.jpg", "media_url_https": "https://pbs.twimg.com/media/CSBZ487UwAAbOro.jpg", "sizes": {"large": {"h": 481, "resize": "fit", "w": 745}, "medium": {"h": 387, "resize": "fit", "w": 600}, "small": {"h": 219, "resize": "fit", "w": 340}, "thumb": {"h": 150, "resize": "crop", "w": 150}}, "source_status_id": 657624381208854528, "source_status_id_str": "657624381208854528", "source_user_id": 14294848, "source_user_id_str": "14294848", "type": "photo", "url": "https://t.co/zbfjVnyu62"}], "retweeted": false, "source": "<a href=\"http://twitter.com/download/iphone\" rel=\"nofollow\">Twitter for iPhone</a>", "text": "Posters for Johnny Bravo and Powerpuff Girls movies aren't real: https://t.co/dW6RQnEs9n https://t.co/zbfjVnyu62", "truncated": false, "urls": {"https://t.co/dW6RQnEs9n": "http://bit.ly/1i15cQS"}, "user": {"created_at": "Tue Oct 20 21:04:20 +0000 2015", "default_profile": true, "description": "Blogger- News- Fashion,Sport,Facts,Quotes,Jokes,Informations ( Dancer, Model, Song Writer and Singer )", "favourites_count": 194, "followers_count": 453, "friends_count": 1854, "id": 3961979173, "lang": "en", "listed_count": 15, "location": "Kuala Lumpur Federal Territory", "name": "Ghost Voice", "profile_background_color": "C0DEED", "profile_background_image_url": "http://abs.twimg.com/images/themes/theme1/bg.png", "profile_background_tile": false, "profile_banner_url": "https://pbs.twimg.com/profile_banners/3961979173/1447241704", "profile_image_url": "https://pbs.twimg.com/profile_images/669302346938105856/8momd3u2_normal.jpg", "profile_link_color": "0084B4", "profile_sidebar_fill_color": "DDEEF6", "profile_text_color": "333333", "protected": false, "screen_name": "ghostvoice00", "statuses_count": 3459, "time_zone": "Pacific Time (US & Canada)", "utc_offset": -28800}}
{"created_at": "Fri Oct 23 18:59:54 +0000 2015", "favorited": false, "id": 657632559170387968, "lang": "en", "retweeted": false, "source": "<a href=\"http://twitterfeed.com\" rel=\"nofollow\">twitterfeed</a>", "text": "Snopes: Movie Posers: Fake movie posters depict Dwayne \"The Rock\" Johnson as Johnny Bravo and Emma Watson, Emm... https://t.co/MLNnSh18tK", "truncated": false, "urls": {"https://t.co/MLNnSh18tK": "http://bit.ly/1i1bcZU"}, "user": {"created_at": "Thu Oct 09 17:37:27 +0000 2008", "description": "Let's make critical thinking easy (and fun).", "favourites_count": 4, "followers_count": 3836, "friends_count": 677, "id": 16669742, "lang": "en", "listed_count": 272, "location": "Everywhere", "name": "Skeptic Network", "profile_background_color": "000000", "profile_background_image_url": "http://pbs.twimg.com/profile_background_images/4759267/fractile_dk.jpg", "profile_background_tile": true, "profile_banner_url": "https://pbs.twimg.com/profile_banners/16669742/1360552274", "profile_image_url": "https://pbs.twimg.com/profile_images/90185083/fractile_sing_SN3_normal.jpg", "profile_link_color": "B00B07", "profile_sidebar_fill_color": "EBECEF", "profile_text_color": "15377E", "protected": false, "screen_name": "SkepNet", "statuses_count": 18316, "time_zone": "Eastern Time (US & Canada)", "utc_offset": -18000}}
{"created_at": "Fri Oct 23 18:59:57 +0000 2015", "favorited": false, "id": 657632570402693121, "lang": "en", "retweeted": false, "source": "<a href=\"http://twitterfeed.com\" rel=\"nofollow\">twitterfeed</a>", "text": "urban legend: Fake movie posters depict Dwayne \"The Rock\" Johnson as Johnny Bravo and Emma Watson, Emma Stone,... https://t.co/GZbEvpkTt6", "truncated": false, "urls": {"https://t.co/GZbEvpkTt6": "http://bit.ly/1PGQWeW"}, "user": {"created_at": "Fri Feb 06 02:21:17 +0000 2009", "default_profile": true, "followers_count": 316, "friends_count": 33, "id": 20211460, "lang": "en", "listed_count": 12, "name": "Urban Legends", "profile_background_color": "C0DEED", "profile_background_image_url": "http://abs.twimg.com/images/themes/theme1/bg.png", "profile_background_tile": false, "profile_image_url": "https://pbs.twimg.com/profile_images/607710950532083713/MvenxG0Z_normal.jpg", "profile_link_color": "0084B4", "profile_sidebar_fill_color": "DDEEF6", "profile_text_color": "333333", "protected": false, "screen_name": "UrbanLegends", "statuses_count": 2202, "time_zone": "Eastern Time (US & Canada)", "utc_offset": -18000}}
{"created_at": "Fri Oct 23 18:59:59 +0000 2015", "favorited": false, "id": 657632578925531136, "lang": "en", "retweeted": false, "source": "<a href=\"http://twitterfeed.com\" rel=\"nofollow\">twitterfeed</a>", "text": "Snopes- Movie Posers https://t.co/BQ2NSMDZ73", "truncated": false, "urls": {"https://t.co/BQ2NSMDZ73": "http://bit.ly/1PGQWeW"}, "user": {"created_at": "Wed Oct 29 14:35:02 +0000 2008", "default_profile": true, "description": "Random Headlines", "followers_count": 122, "friends_count": 13, "id": 17042353, "lang": "en", "listed_count": 3, "location": "Random", "name": "Headline Post", "profile_background_color": "C0DEED", "profile_background_image_url": "http://abs.twimg.com/images/themes/theme1/bg.png", "profile_background_tile": false, "profile_image_url": "https://pbs.twimg.com/profile_images/63101611/headline_normal.jpg", "profile_link_color": "0084B4", "profile_sidebar_fill_color": "DDEEF6", "profile_text_color": "333333", "protected": false, "screen_name": "headlinepost", "statuses_count": 15906, "time_zone": "Central Time (US & Canada)", "utc_offset": -21600}}
{"created_at": "Fri Oct 23 21:26:53 +0000 2015", "favorited": false, "hashtags": ["Snopes"], "id": 657669546917146624, "lang": "en", "retweeted": false, "source": "<a href=\"http://momknowsshopping.com/UFOParanormal\" rel=\"nofollow\">UFOParanormalNews</a>", "text": "#Snopes  Fake movie posters depict Dwayne The Rock Johnson as Johnny Bravo and Emma https://t.co/vb92Qq2l4a", "truncated": false, "urls": {"https://t.co/vb92Qq2l4a": "http://goo.gl/qnDMmM"}, "user": {"created_at": "Wed Oct 01 13:34:46 +0000 2014", "description": "We provide the latest news on #UFO's, #Paranormal, #Ghosts and everything that is strange or weird. Plus #Software, #Camera's and #Computer items.", "favourites_count": 3, "followers_count": 12344, "friends_count": 11549, "geo_enabled": true, "id": 2797963749, "lang": "en", "listed_count": 412, "name": "UFO Paranormal", "profile_background_color": "000000", "profile_background_image_url": "http://abs.twimg.com/images/themes/theme1/bg.png", "profile_background_tile": false, "profile_banner_url": "https://pbs.twimg.com/profile_banners/2797963749/1419626990", "profile_image_url": "https://pbs.twimg.com/profile_images/517311356198858753/OkOTy-q6_normal.jpeg", "profile_link_color": "FA743E", "profile_sidebar_fill_color": "000000", "profile_text_color": "000000", "protected": false, "screen_name": "UFOParanormNews", "statuses_count": 77024, "url": "https://t.co/I4rmVNErYQ"}}
{"created_at": "Fri Oct 23 23:39:48 +0000 2015", "favorited": false, "id": 657702997502377984, "lang": "en", "retweet_count": 1, "retweeted": false, "source": "<a href=\"http://twitter.com\" rel=\"nofollow\">Twitter Web Client</a>", "text": "FAKE!! https://t.co/rimyttT6lc https://t.co/wCNwTDh6hp", "truncated": false, "urls": {"https://t.co/rimyttT6lc": "http://www.snopes.com/johny-bravo-the-rock-powerpuff-girls/", "https://t.co/wCNwTDh6hp": "https://twitter.com/DavidNnwoka/status/656259968061087744"}, "user": {"created_at": "Mon Nov 03 13:36:32 +0000 2008", "description": "Digital Marketer. Husband. Dad.\nThere is nothing noble in being superior to your fellow man. True nobility is being superior to your former self - Hemingway", "favourites_count": 5757, "followers_count": 20008, "friends_count": 2934, "geo_enabled": true, "id": 17130422, "lang": "en", "listed_count": 94, "location": "Lagos, Nigeria", "name": "Gbenga Olorunpomi", "profile_background_color": "EDECE9", "profile_background_image_url": "http://pbs.twimg.com/profile_background_images/551842995901698048/lcNuhkUd.jpeg", "profile_background_tile": true, "profile_banner_url": "https://pbs.twimg.com/profile_banners/17130422/1441349348", "profile_image_url": "https://pbs.twimg.com/profile_images/684616384328929280/JH9xhB6t_normal.jpg", "profile_link_color": "9266CC", "profile_sidebar_fill_color": "E3E2DE", "profile_text_color": "634047", "protected": false, "screen_name": "GbengaGOLD", "statuses_count": 129947, "time_zone": "West Central Africa", "url": "https://t.co/vyzOBIl6KI", "utc_offset": 3600}}
{"created_at": "Sat Oct 24 01:29:00 +0000 2015", "favorited": false, "id": 657730476027719680, "lang": "en", "retweeted": false, "source": "<a href=\"http://twitter.com/#!/download/ipad\" rel=\"nofollow\">Twitter for iPad</a>", "text": "In October 2015, fake movie posters depicting Dwayne \"The Rock\" Johnson as Johnny Bravo and Emma Watson... https://t.co/IKaWvytnEb", "truncated": false, "urls": {"https://t.co/IKaWvytnEb": "http://www.snopes.com/johny-bravo-the-rock-powerpuff-girls/"}, "user": {"created_at": "Mon Apr 02 15:43:01 +0000 2007", "description": "Geek mom, Night Elf (main), currently braindead.", "favourites_count": 3626, "followers_count": 354, "friends_count": 355, "id": 3224661, "lang": "en", "listed_count": 28, "location": "Minnesota", "name": "Wendy Comeau", "profile_background_color": "9AE4E8", "profile_background_image_url": "http://abs.twimg.com/images/themes/theme1/bg.png", "profile_background_tile": false, "profile_image_url": "https://pbs.twimg.com/profile_images/606794427/wendy.comeau_gmail.com_d95f1456_normal.jpg", "profile_link_color": "0000FF", "profile_sidebar_fill_color": "E0FF92", "profile_text_color": "000000", "protected": false, "screen_name": "Kaji", "statuses_count": 39184, "time_zone": "Central Time (US & Canada)", "url": "http://t.co/5kLnS0dd2s", "utc_offset": -21600}}
{"created_at": "Sat Oct 24 04:18:05 +0000 2015", "favorited": false, "id": 657773029649350658, "lang": "en", "retweeted": false, "source": "<a href=\"http://www.facebook.com/twitter\" rel=\"nofollow\">Facebook</a>", "text": "FALSE: Johnny Bravo and Powerpuff Girls Movie Posters https://t.co/SoKqmqlYcY", "truncated": false, "urls": {"https://t.co/SoKqmqlYcY": "http://fb.me/7CpX2Ckju"}, "user": {"created_at": "Mon Jan 03 22:47:57 +0000 2011", "description": "Learning to live One Day @ A Time!!!!", "favourites_count": 32, "followers_count": 321, "friends_count": 1218, "id": 233708501, "lang": "en", "listed_count": 12, "location": "Pinson, AL", "name": "April Gaddis", "profile_background_color": "C0DEED", "profile_background_image_url": "http://abs.twimg.com/images/themes/theme1/bg.png", "profile_background_tile": false, "profile_banner_url": "https://pbs.twimg.com/profile_banners/233708501/1407535011", "profile_image_url": "https://pbs.twimg.com/profile_images/555999968733847552/QKyE5wkq_normal.jpeg", "profile_link_color": "9266CC", "profile_sidebar_fill_color": "DDEEF6", "profile_text_color": "333333", "protected": false, "screen_name": "aprilgaddis", "statuses_count": 34833}}
{"created_at": "Sat Oct 24 08:37:03 +0000 2015", "favorited": false, "id": 657838200308826112, "lang": "en", "retweeted": false, "source": "<a href=\"http://mobile.twitter.com\" rel=\"nofollow\">Mobile Web</a>", "text": "Movie Posers https://t.co/fFN9uvPXgs", "truncated": false, "urls": {"https://t.co/fFN9uvPXgs": "http://www.snopes.com/johny-bravo-the-rock-powerpuff-girls/"}, "user": {"created_at": "Sat May 24 06:22:02 +0000 2014", "favourites_count": 25, "followers_count": 35, "friends_count": 587, "geo_enabled": true, "id": 2519658398, "lang": "en", "listed_count": 1, "location": "New York NY", "name": "My Info Page", "profile_background_color": "022330", "profile_background_image_url": "http://abs.twimg.com/images/themes/theme15/bg.png", "profile_background_tile": false, "profile_banner_url": "https://pbs.twimg.com/profile_banners/2519658398/1405469159", "profile_image_url": "https://pbs.twimg.com/profile_images/550478605999161344/PHAgXw3N_normal.jpeg", "profile_link_color": "0084B4", "profile_sidebar_fill_color": "C0DFEC", "profile_text_color": "333333", "protected": false, "screen_name": "myinfopage", "statuses_count": 325, "time_zone": "Atlantic Time (Canada)", "url": "http://t.co/y5zBdWD6BW", "utc_offset": -14400}}
{"created_at": "Sat Oct 24 14:56:48 +0000 2015", "favorited": false, "id": 657933766447337472, "lang": "en", "retweeted": false, "source": "<a href=\"http://twitter.com/download/iphone\" rel=\"nofollow\">Twitter for iPhone</a>", "text": "FALSE: Johnny Bravo and Powerpuff Girls Movie Posters https://t.co/pV0alIEGzi", "truncated": false, "urls": {"https://t.co/pV0alIEGzi": "http://www.snopes.com/johny-bravo-the-rock-powerpuff-girls/"}, "user": {"created_at": "Wed Mar 11 16:34:24 +0000 2009", "description": "Juz an Average Joe", "favourites_count": 420, "followers_count": 199, "friends_count": 629, "id": 23787072, "lang": "en", "listed_count": 20, "location": "Bandar Shah Alam, Selangor", "name": "Tengku Azlan Shah TJ", "profile_background_color": "1A1B1F", "profile_background_image_url": "http://pbs.twimg.com/profile_background_images/768734385/e68308dbeb2eff4db9294e05a97395c4.jpeg", "profile_background_tile": false, "profile_banner_url": "https://pbs.twimg.com/profile_banners/23787072/1441577937", "profile_image_url": "https://pbs.twimg.com/profile_images/536626294725672960/QcmLT3Ca_normal.jpeg", "profile_link_color": "2FC2EF", "profile_sidebar_fill_color": "252429", "profile_text_color": "666666", "protected": false, "screen_name": "AzlanTJ", "statuses_count": 8627, "time_zone": "Kuala Lumpur", "utc_offset": 28800}}
{"created_at": "Sat Oct 24 17:13:42 +0000 2015", "favorited": false, "id": 657968217248235520, "lang": "en", "retweeted": false, "source": "<a href=\"http://www.facebook.com/twitter\" rel=\"nofollow\">Facebook</a>", "text": "The movie posters of \"The Rock\" as Johnny Bravo and Emma Watson, Emma Stone, and Ellen Page as The Powerpuff... https://t.co/vt0LVZ0HtS", "truncated": false, "urls": {"https://t.co/vt0LVZ0HtS": "http://fb.me/3XC4sx39D"}, "user": {"created_at": "Tue Jun 09 20:45:21 +0000 2009", "description": "Red Zone Fandom: event photographers supporting cosplayers & fans of fantasy, Sci-Fi, RPG, gaming, card games, Anime, Cosplay, Furs, and much more.", "favourites_count": 5, "followers_count": 100, "friends_count": 124, "id": 45939281, "lang": "en", "listed_count": 2, "name": "Red Zone Fandom", "profile_background_color": "EBEBEB", "profile_background_image_url": "http://pbs.twimg.com/profile_background_images/220937634/rz-net-wallpaper.png", "profile_background_tile": true, "profile_banner_url": "https://pbs.twimg.com/profile_banners/45939281/1398454348", "profile_image_url": "https://pbs.twimg.com/profile_images/630112949030359040/9YI_WtzO_normal.jpg", "profile_link_color": "990000", "profile_sidebar_fill_color": "F3F3F3", "profile_text_color": "333333", "protected": false, "screen_name": "redzonefandom", "statuses_count": 3398, "time_zone": "Mountain Time (US & Canada)", "url": "http://t.co/iXP3bHwgwP", "utc_offset": -25200}}
{"created_at": "Sun Oct 25 03:30:43 +0000 2015", "favorited": false, "id": 658123498162909186, "lang": "en", "media": [{"display_url": "pic.twitter.com/nbAHXM8Hdq", "expanded_url": "http://twitter.com/DWLuttrell/status/658123498162909186/photo/1", "id": 658123410975887361, "id_str": "658123410975887361", "indices": [77, 100], "media_url": "http://pbs.twimg.com/media/CSIfwWGWEAE4GX2.jpg", "media_url_https": "https://pbs.twimg.com/media/CSIfwWGWEAE4GX2.jpg", "sizes": {"large": {"h": 960, "resize": "fit", "w": 666}, "medium": {"h": 864, "resize": "fit", "w": 600}, "small": {"h": 490, "resize": "fit", "w": 340}, "thumb": {"h": 150, "resize": "crop", "w": 150}}, "type": "photo", "url": "https://t.co/nbAHXM8Hdq"}], "retweeted": false, "source": "<a href=\"https://about.twitter.com/products/tweetdeck\" rel=\"nofollow\">TweetDeck</a>", "text": "lol https://t.co/QgVry0euNm That's funny. ...people. https://t.co/xyf06nvGBK https://t.co/nbAHXM8Hdq", "truncated": false, "urls": {"https://t.co/QgVry0euNm": "https://twitter.com/DWLuttrell/status/265671442174181377", "https://t.co/xyf06nvGBK": "http://www.snopes.com/johny-bravo-the-rock-powerpuff-girls/"}, "user": {"created_at": "Wed May 04 03:13:14 +0000 2011", "description": "Associates of Science in Computer Information Technology: Summa Cum Laude 2015; Bass Guitar Player; Published Poet", "followers_count": 1834, "friends_count": 1691, "id": 292715397, "lang": "en", "listed_count": 25, "location": "Kentucky, USA", "name": "D. W. Luttrell", "profile_background_color": "3B94D9", "profile_background_image_url": "http://pbs.twimg.com/profile_background_images/535576860667551744/7So8bkGm.jpeg", "profile_background_tile": true, "profile_banner_url": "https://pbs.twimg.com/profile_banners/292715397/1446608566", "profile_image_url": "https://pbs.twimg.com/profile_images/680721602477191168/lv4hxNMA_normal.jpg", "profile_link_color": "3B94D9", "profile_sidebar_fill_color": "FFFFFF", "profile_text_color": "092592", "protected": false, "screen_name": "DWLuttrell", "statuses_count": 149531, "time_zone": "Quito", "url": "https://t.co/X1PkWpk71P", "utc_offset": -18000}}
{"created_at": "Thu Oct 29 17:30:18 +0000 2015", "favorited": false, "id": 659784336019820544, "in_reply_to_screen_name": "BeingKushSharma", "in_reply_to_status_id": 659783103653609472, "in_reply_to_user_id": 585569365, "lang": "en", "retweet_count": 2, "retweeted": false, "source": "<a href=\"http://twitter.com/download/android\" rel=\"nofollow\">Twitter for Android</a>", "text": "@BeingKushSharma @LoyalSalmanFan Powerpuff girls.. Dexter's laboratory.. Jackson's. Captain Planet.. Johny Bravo. Popeye..", "truncated": false, "user": {"created_at": "Sat May 07 11:01:37 +0000 2011", "description": "A https://t.co/jBKtxjpiEw StUdEnT|MuSiC LoVeR|CrIcKeTCrazzy(\u2665 @BeingSalmanKhan Addicted\u2665&Admirer)TrueFangirl\u2665  PROUDINDIAN #28Oct15 Salman\u2665 Replied{Wanna Meet}", "favourites_count": 4730, "followers_count": 1586, "friends_count": 469, "geo_enabled": true, "id": 294556897, "lang": "en", "listed_count": 39, "location": "Jabalpur, Madhya Pradesh", "name": "Prajakta ~", "profile_background_color": "FFFFFF", "profile_background_image_url": "http://pbs.twimg.com/profile_background_images/378800000165693023/AkDQZucT.jpeg", "profile_background_tile": true, "profile_banner_url": "https://pbs.twimg.com/profile_banners/294556897/1452619818", "profile_image_url": "https://pbs.twimg.com/profile_images/687193761672114176/FAJ24zYI_normal.jpg", "profile_link_color": "E6275D", "profile_sidebar_fill_color": "111A1F", "profile_text_color": "E36930", "protected": false, "screen_name": "cool_nikkki", "statuses_count": 47260, "time_zone": "Mumbai", "url": "https://t.co/x9C3b3WkGo", "utc_offset": 19800}, "user_mentions": [{"id": 585569365, "name": "Amoroso", "screen_name": "BeingKushSharma"}, {"id": 1327335133, "name": "I\u0535\u015a R\u0251\u0575..!", "screen_name": "LoyalSalmanFan"}]}
